<?xml version="1.0" encoding="UTF-8"?>
<!DOCTYPE mapper PUBLIC "-//mybatis.org//DTD Mapper 3.0//EN" "http://mybatis.org/dtd/mybatis-3-mapper.dtd">

<mapper namespace="xin.tianchuang.modules.externalApi.qichacha.dao.QichachaDataPatentDao">

	<!-- 可根据自己的需求，是否要使用 -->
    <resultMap type="xin.tianchuang.modules.externalApi.qichacha.entity.QichachaDataPatentEntity" id="qichachaDataPatentMap">
        <result property="id" column="id"/>
        <result property="entName" column="ent_name"/>
        <result property="creditCode" column="credit_code"/>
        <result property="documentTypes" column="document_types"/>
        <result property="agent" column="agent"/>
        <result property="legalStatusDate" column="legal_status_date"/>
        <result property="primaryExaminer" column="primary_examiner"/>
        <result property="assiantExaminer" column="assiant_examiner"/>
        <result property="cites" column="cites"/>
        <result property="otherReferences" column="other_references"/>
        <result property="patentImage" column="patent_image"/>
        <result property="ipcList" column="ipc_list"/>
        <result property="applicationNumber" column="application_number"/>
        <result property="applicationDate" column="application_date"/>
        <result property="publicationNumber" column="publication_number"/>
        <result property="publicationDate" column="publication_date"/>
        <result property="legalStatusDesc" column="legal_status_desc"/>
        <result property="title" column="title"/>
        <result property="abstractText" column="abstract_text"/>
        <result property="agency" column="agency"/>
        <result property="kindCodeDesc" column="kind_code_desc"/>
        <result property="ipcDesc" column="ipc_desc"/>
        <result property="inventorStringList" column="inventor_string_list"/>
        <result property="assigneestringList" column="assigneestring_list"/>
        <result property="patentLegalHistory" column="patent_legal_history"/>
        <result property="dataStatus" column="data_status"/>
        <result property="createTime" column="create_time"/>
        <result property="creator" column="creator"/>
        <result property="updateTime" column="update_time"/>
        <result property="updater" column="updater"/>
    </resultMap>


</mapper>